---
title: 0.1 - Computer Programs     # TITLE for the post
# author: Starlight                 # uncomment to override author name, by default its Starlight

date: 2023-12-03 02:25:00 +0500     # YYYY-MM-DD HH:MM:SS +/-TTTT // Add Future Date & Time for planned future release

categories: [Programming Languages, -Programming 101]             # [TOP_CATEGORY, SUB_CATEGORY] 
tags: [programs, codes, softwares]   # [TAG] 'TAG' names should always be lowercase & seperated by comma

# pin: true         # uncomment to pin
# toc: false        # uncomment to turn off Table Of Content for this post

#math: true         # (override) uncomment to use MathJax Mathematics for this post
#mermaid: true       # (override) uncomment to use Mermaid diagram functionality for this post

image:      
  path: /assets/img/posts/computer-programs.jpg   # image path. forward slash (/)
  lqip: data:image/jpg;base64,UklGRi4AAABXRUJQVlA4ICIAAACQAQCdASoKAAYAAkA4JZwAAudGFIAA/v2d8Pz2XIlelmAA
  alt: Computer Programs   # displayed under the image (caption) 

# render_with_liquid: false           # comment or set bool true to use Liquid Parsing

---

"The keyboard is our pen, and code is our language. Let's embark on a linguistic adventure through the world of computer programs, where syntax and semantics come together to create the poetry of the digital age."

## Program

A [program](https://en.wikipedia.org/wiki/Computer_program) is a set of instructions written in a programming language that is executed by a computer to perform a specific task. The computer executes these instructions based on the provided program. Unlike algorithms, programs are language-specific and provide detailed instructions with the exact syntax required for a computer to understand and execute. 

An individual who creates programs is referred to as [programmer](https://en.wikipedia.org/wiki/Programmer), a coder, a software developer or a software engineer. Programmers use algorithms as a basis to write programs, translating the logical steps into a language that a computer can comprehend. 

## Types of Codes

In the context of computer programming, there are several types of code, each serving a specific purpose in the development and execution of software.

### Source Code

- [Source code](https://en.wikipedia.org/wiki/Source_code) is the human-readable form of a program written by a programmer using a programming language.
- It consists of statements and instructions written in a format that can be understood by humans. This code is typically written in a high-level programming language, such as Python, Java, C++, or others.
- Source code needs to be translated into "machine code" before it can be executed by a computer's central processing unit (CPU).
- **Source program** is a term used to describe the original code written by a programmer, typically in a form that is easy for humans to read and understand.

```c++
// Source Code example
#include <iostream>

int main() {
    std::cout << "Hello, World!" << std::endl;
    return 0;
}
```

### Object Code

- [Object code](https://en.wikipedia.org/wiki/Object_code) is the machine-readable, binary representation of the program that is generated by a compiler or an assembler.
-  It is an intermediate step between the human-readable source code and the machine-executable code.
- When you write a program in a high-level programming language (source code), you need to use a compiler or an interpreter to convert that source code into machine code. The output of this compilation process is often referred to as **object code**. Object code is not human-readable and is specific to the computer architecture for which it was generated or compiled.
- While less readable than the original source code, object code is more human-readable than machine code. It is a binary representation with some level of structure, but it still requires translation by the computer's hardware.
-  Object code needs further processing, either by an assembler (in the case of assembly language) or a linker (in the case of compiled high-level languages), to produce the final machine code.
-  **Object program** is another term used to describe the result of the compilation or assembly process.

### Machine Code

- [Machine code](https://en.wikipedia.org/wiki/Machine_code) is a set of instructions written in binary or hexadecimal format that is directly understandable and executable by a computer's central processing unit (CPU).
- It represents the lowest level of programming language and is specific to the architecture of the computer's CPU.
- It is not human-readable and is often in the form of raw binary instructions, making it challenging for programmers to understand or modify directly.
- Each instruction in machine code corresponds to a specific operation that the CPU can perform, such as arithmetic calculations, data movement, or control flow operations.

The x86 assembly instruction `mov eax, 5` moves or loads the value 5 into the `eax` register. The corresponding machine code in binary might look like this:

```
; Machine Code Example (Binary)

; mov eax, 5
10111000 00000101 00000000 00000000 00000101
```

In this example, each group of eight binary digits (bits) represents a byte. The `10111000` is the opcode for the `mov` instruction with the destination register `eax`. The `00000101` represents the immediate value 5 in little-endian format (common in x86 architecture). The rest of the zeros are padding.

### ByteCode

- [Bytecode](https://en.wikipedia.org/wiki/Bytecode) is an intermediate representation of a program that is generated by a compiler or an interpreter.
- It is not directly executed by the CPU but is instead interpreted or translated by a virtual machine or an interpreter at runtime.
- Bytecode is typically platform-independent, allowing the same bytecode to be executed on different systems with the appropriate virtual machine or interpreter.
- Java bytecode is a well-known example, used in Java programming, where it is executed by the Java Virtual Machine (JVM).

```java
// Java Source Code
public class BytecodeExample {
    public static void main(String[] args) {
        int a = 5;
        int b = 3;
        int result = a + b;
        System.out.println("Result: " + result);
    }
}
```

After compiling the above Java code, you would get bytecode. This bytecode is in a format that can be executed by the Java Virtual Machine (JVM). The actual bytecode generated by a Java compiler may be more complex and include additional instructions and metadata. Below is a simplified representation of Java bytecode for the above Java source code:

```
// Simplified Java Bytecode
0: iconst_5            // Push the integer constant 5 onto the stack
3: istore_1            // Pop the top value from the stack and store it in local variable 1 (a)
6: iconst_3            // Push the integer constant 3 onto the stack
9: istore_2            // Pop the top value from the stack and store it in local variable 2 (b)
12: iload_1            // Load the value of local variable 1 (a) onto the stack
13: iload_2            // Load the value of local variable 2 (b) onto the stack
14: iadd               // Add the top two values on the stack
15: istore_3           // Pop the result and store it in local variable 3 (result)
18: getstatic          #2  // Get the System.out field
21: new                #3  // Create a new StringBuilder
24: dup
25: ldc                #4  // Push the string "Result: " onto the stack
27: invokespecial      #5  // Invoke the StringBuilder constructor
30: iload_3                // Load the value of local variable 3 (result) onto the stack
31: invokevirtual      #6  // Invoke the append method on the StringBuilder
34: invokevirtual      #7  // Invoke the toString method on the StringBuilder
37: invokevirtual      #8  // Invoke the println method on System.out
```

### MicroCode

- [Microcode](https://en.wikipedia.org/wiki/Microcode) is a layer of low-level instructions that reside between machine code and the hardware components of a CPU.
- It is a set of instructions and control signals that are used to implement the architecture and functionality of the CPU.
- Microcode is specific to the CPU's design and is responsible for translating machine code instructions into signals that control the CPU's internal components.
- Programmers usually interact with machine code, while microcode is implemented by CPU manufacturers to execute machine code on the underlying hardware.
- Microcode is stored in the control unit's firmware and is not directly visible or accessible to programmers.

```
; Microcode Example (Hypothetical Microinstructions)
0001: LoadRegister(Register.EAX, 5)
0002: AddRegisters(Register.EAX, Register.EAX, 3)
0003: MoveRegister(Register.EBX, Register.EAX)
0004: InvokeSystemCall(SystemCall.EXIT)
```

## Software

[Software](https://en.wikipedia.org/wiki/Software) refers to a set of instructions or programs that tell a computer how to perform specific tasks. It encompasses a wide range of applications, scripts, and programs that enable various functionalities on computing devices. Software is a crucial component of modern technology and is essential for the operation of computers, smartphones, and other electronic devices. For instance, word processors serve as applications designed for tasks such as letter, paper, and book composition.

There are several types of software, broadly categorized into two main groups:

### System Software

[System Software](https://en.wikipedia.org/wiki/System_software) is reponsible for managing the computer. It provides a platform for other software to run and interact directly with computer hardware. System software is essential for the proper functioning of a computer, providing a foundation for the execution of application software and ensuring effective communication between hardware and software components.

- **Operating Systems (OS)**: The core software that manages hardware resources, provides services for computer programs, and acts as an intermediary between the user and the computer hardware. Examples include Microsoft Windows, macOS, Linux, and Android.
- **Device Drivers**: Programs that allow the operating system to communicate with and control specific hardware devices, such as printers, graphics cards, and input devices.
- **Utilities**: Tools and programs that perform various tasks related to system maintenance, file management, and security. Examples include antivirus software, disk cleanup utilities, and backup tools.

### Application Software

[Application software](https://en.wikipedia.org/wiki/Application_software) is designed to perform specific tasks or functions for end-users. Unlike system software, which facilitates the operation of the computer system, application software directly fulfills the needs or desires of users.

- **Word Processors**: Software used for creating, editing, and formatting text documents. Examples include Microsoft Word, Google Docs, and LibreOffice Writer.
- **Database Software**: Programs that manage and organize large sets of data. Examples include Microsoft Access, MySQL, and Oracle Database.
- **Web Browsers**: Applications that allow users to access and navigate the internet. Examples include Google Chrome, Mozilla Firefox, and Microsoft Edge.
- **Games and Entertainment Software**: Designed for entertainment purposes, including video games, media players, and streaming applications.
- **Graphics and Multimedia Software**: Used for creating and editing visual and multimedia content. Examples include Adobe Photoshop for image editing, Adobe Premiere for video editing, and Audacity for audio editing.
